{
    "general": {
      "title": "RESTORATIVE YOGA",
      "subtitle": "Rest and Relax",
      "description": "Guided breath awareness, meditation and Restorative poses with the support of props.",
      "orgName": "Simply Massage and Associates",
      "location": "168 Curtis St. Entrance is on Catharine St. (Teal Door)",
      "fee": 10
    },
    "header": {
      "day": "Thursday",
      "month": "May",
      "daysAvailable": "2, 9, 16, 23, 30",
      "times": "7-8pm",
      "colour": "#FFFFFF"
    },
    "footer": {
      "day": "Friday",
      "month": "May",
      "daysAvailable": "3, 10, 17, 23, 31",
      "times": "7-8pm",
      "colour": "#FFFFFF"
    }
  }